gsheet_api/__init__.py
gsheet_api/gsheet_api.py
gsheet_api-0.1.4.dist-info/LICENSE
gsheet_api-0.1.4.dist-info/METADATA
gsheet_api-0.1.4.dist-info/WHEEL
gsheet_api-0.1.4.dist-info/top_level.txt
gsheet_api-0.1.4.dist-info/RECORD
