Metadata-Version: 2.1
Name: gsheet-api
Version: 0.1.4
Summary: Easily and efficiently manage a Google Sheet
Home-page: https://github.com/brandenc40/gsheet-api
Author: Branden Colen
Author-email: brandencolen@gmail.com
License: UNKNOWN
Keywords: google sheet api pandas dataframe
Platform: UNKNOWN
Classifier: Programming Language :: Python :: 3
Classifier: Programming Language :: Python :: 2
Classifier: License :: OSI Approved :: MIT License
Classifier: Operating System :: OS Independent
Classifier: Development Status :: 4 - Beta
Requires-Dist: gspread
Requires-Dist: gspread-dataframe
Requires-Dist: pytz
Requires-Dist: oauth2client
